<bml id="bml1" composition="MERGE" xmlns="http://www.bml-initiative.org/bml/bml-1.0">
   <constraint xmlns="http://www.bml-initiative.org/bml/bml-1.0">
      <synchronize xmlns="http://www.bml-initiative.org/bml/bml-1.0">
         <sync ref="bml1:gaze1:end" xmlns="http://www.bml-initiative.org/bml/bml-1.0"/>
         <sync ref="bml1:headmotion:end+0.5" xmlns="http://www.bml-initiative.org/bml/bml-1.0"/>
      </synchronize>
   </constraint>
   <constraint xmlns="http://www.bml-initiative.org/bml/bml-1.0">
      <synchronize xmlns="http://www.bml-initiative.org/bml/bml-1.0">
         <sync ref="bml1:gaze1:start" xmlns="http://www.bml-initiative.org/bml/bml-1.0"/>
         <sync ref="bml1:bml:start" xmlns="http://www.bml-initiative.org/bml/bml-1.0"/>
      </synchronize>
   </constraint>
   <keyframe id="bml1:headmotion" xmlns="http://hmi.ewi.utwente.nl/bmlt"><SkeletonInterpolator encoding="R" rotationEncoding="Quat" parts="skullbase">
   0.0 1.0 0.0 0.0 0.0
   0.008333333333333333 1.0 0.0 0.0 0.0
   0.016666666666666666 1.0 0.0 0.0 0.0
   0.025 1.0 0.0 0.0 0.0
   0.03333333333333333 1.0 0.0 0.0 0.0
   0.041666666666666664 1.0 0.0 0.0 0.0
   0.05 0.9999999 2.2493777E-4 2.89193E-4 3.7586867E-4
   0.058333333333333334 0.9999995 5.244476E-4 1.4268502E-4 7.896075E-4
   0.06666666666666667 0.9999989 4.862873E-4 1.8336553E-4 0.0013722964
   0.075 0.9999981 4.4392818E-4 6.33852E-4 0.0018041661
   0.08333333333333333 0.99999726 3.9858636E-4 0.0013512525 0.001867392
   0.09166666666666666 0.9999955 6.93291E-4 0.0019447147 0.0021700887
   0.1 0.9999934 0.0011460237 0.0022458965 0.0026275858
   0.10833333333333334 0.99999076 0.0014609991 0.002795967 0.0029120136
   0.11666666666666667 0.9999878 0.0018003889 0.0031105415 0.0033949227
   0.125 0.99998474 0.0022004698 0.0035485697 0.0036229102
   0.13333333333333333 0.9999812 0.0024074323 0.00393128 0.0040408596
   0.14166666666666666 0.9999779 0.0028055583 0.004269808 0.0042616064
   0.15 0.99997425 0.0029438217 0.0047032875 0.0045502256
   0.15833333333333333 0.9999708 0.0032428247 0.0049221227 0.0048636454
   0.16666666666666666 0.99996793 0.0035717962 0.00521186 0.004925479
   0.175 0.9999644 0.003657571 0.0056136255 0.005124303
   0.18333333333333332 0.9999609 0.0039001824 0.0057558645 0.0054687625
   0.19166666666666665 0.9999609 0.0039001824 0.0057558645 0.0054687625
   0.2 0.9999609 0.0039001824 0.0057558645 0.0054687625
   0.20833333333333334 0.9999609 0.0039001824 0.0057558645 0.0054687625
   0.21666666666666667 0.99995667 0.0041709994 0.0060100243 0.0057546576
   0.225 0.99995166 0.0043225475 0.0062030707 0.006287862
   0.23333333333333334 0.9999463 0.0043077595 0.0066269264 0.0067012017
   0.24166666666666667 0.999935 0.004262409 0.0074567692 0.0075057116
   0.25 0.99992114 0.00388833 0.008378753 0.008510763
   0.2583333333333333 0.999908 0.003159206 0.009159141 0.009495407
   0.26666666666666666 0.9998971 0.0021714757 0.009764862 0.010279281
   0.275 0.9998892 9.924714E-4 0.010132226 0.010857925
   0.2833333333333333 0.99987745 -1.06878804E-4 0.010826368 0.011304885
   0.2916666666666667 0.99986315 -0.0010411956 0.011789538 0.011560056
   0.3 0.9998512 -0.0022162679 0.012514871 0.011660993
   0.30833333333333335 0.99984145 -0.00357485 0.012914668 0.011727211
   0.31666666666666665 0.9998238 -0.00482008 0.013551004 0.012062056
   0.325 0.99980736 -0.0061677517 0.013824603 0.012491383
   0.3333333333333333 0.9997837 -0.007339574 0.014396312 0.013092837
   0.3416666666666667 0.9997551 -0.008218925 0.01515794 0.013872503
   0.35 0.9997241 -0.00874408 0.01604378 0.014762598
   0.35833333333333334 0.9997108 -0.0089766495 0.016403243 0.01512306
   0.36666666666666664 0.99970126 -0.009471027 0.016595017 0.015240072
   0.375 0.9996879 -0.009701721 0.01696379 0.015563458
   0.3833333333333333 0.9996772 -0.009935787 0.017454058 0.015562485
   0.39166666666666666 0.99967027 -0.010352991 0.017785445 0.015358406
   0.4 0.99965763 -0.010675499 0.018301567 0.0153544685
   0.4083333333333333 0.99964124 -0.0108658 0.018852048 0.015618189
   0.4166666666666667 0.9996305 -0.011082259 0.019391743 0.015493256
   0.425 0.99961656 -0.01147703 0.019715216 0.01569615
   0.43333333333333335 0.9996083 -0.011763716 0.020126037 0.015486349
   0.44166666666666665 0.99959296 -0.011929207 0.020629795 0.015683617
   0.45 0.9995775 -0.012431058 0.02095657 0.015843736
   0.4583333333333333 0.9995504 -0.013304115 0.021503786 0.016112335
   0.4666666666666667 0.9995122 -0.014165635 0.022396768 0.016524803
   0.475 0.9994923 -0.014620235 0.02283931 0.01672766
   0.48333333333333334 0.99945796 -0.015401211 0.023569014 0.017062616
   0.49166666666666664 0.9994141 -0.016066747 0.024496874 0.017697373
   0.5 0.9993699 -0.01638874 0.025566025 0.018372612
   0.5083333333333333 0.9993283 -0.016385706 0.026551811 0.01921933
   0.5166666666666666 0.9992907 -0.016127778 0.027661333 0.01982139
   0.525 0.9992507 -0.015917758 0.028555695 0.020716412
   0.5333333333333333 0.99921906 -0.015366769 0.02939188 0.021475662
   0.5416666666666666 0.9991833 -0.015017759 0.030039107 0.022469314
   0.55 0.9991571 -0.014350711 0.030583162 0.023320928
   0.5583333333333333 0.99912184 -0.013845506 0.031411685 0.024022657
   0.5666666666666667 0.9990959 -0.013108838 0.032220542 0.024439868
   0.575 0.99907166 -0.012311139 0.032772254 0.025104286
   0.5833333333333334 0.99905396 -0.011488038 0.03298703 0.025905998
   0.5916666666666667 0.99904346 -0.010468019 0.033248138 0.026404472
   0.6 0.99901724 -0.009617346 0.03381617 0.02699093
   0.6083333333333333 0.9990042 -0.008576542 0.03423279 0.02729938
   0.6166666666666667 0.99897814 -0.007722214 0.034959815 0.027583806
   0.625 0.9989397 -0.007057346 0.035715643 0.02817951
   0.6333333333333333 0.9989027 -0.006389625 0.036646314 0.028455045
   0.6416666666666666 0.9988705 -0.005490554 0.03733857 0.02886883
   0.65 0.9988448 -0.0044821957 0.03809676 0.02894069
   0.6583333333333333 0.9988282 -0.0034216985 0.03886433 0.028638992
   0.6666666666666666 0.99881583 -0.0025153228 0.039712906 0.02798994
   0.675 0.99881095 -0.0021468757 0.040060572 0.0276992
   0.6833333333333333 0.9988036 -0.0020385173 0.040522173 0.027296733
   0.6916666666666667 0.99878484 -0.0019197774 0.041091207 0.027142135
   0.7 0.9987771 -0.001644149 0.041503962 0.026814215
   0.7083333333333334 0.99877363 -0.0016273819 0.041873235 0.026366267
   0.7166666666666667 0.9987572 -0.0013908463 0.04246199 0.026060248
   0.725 0.9987281 -8.7414833E-4 0.043171488 0.026030986
   0.7333333333333333 0.9986798 5.451953E-5 0.04431125 0.025983116
   0.7416666666666667 0.99865496 5.212859E-4 0.044883896 0.025950918
   0.75 0.99861056 0.0013350785 0.045886174 0.025877772
   0.7583333333333333 0.99855125 0.0024472654 0.047046702 0.025999933
   0.7666666666666666 0.9984959 0.0035249281 0.048277568 0.025744831
   0.775 0.9984521 0.004376962 0.04937334 0.025227753
   0.7833333333333333 0.9984195 0.0050123017 0.050360095 0.024437496
   0.7916666666666666 0.99837047 0.0057606404 0.05146981 0.023960229
   0.8 0.9983265 0.006267733 0.052599072 0.023202099
   0.8083333333333333 0.9982933 0.0065461616 0.053630278 0.022167739
   0.8166666666666667 0.99827147 0.0065480657 0.05452903 0.02092304
   0.825 0.99823636 0.006882107 0.05555995 0.019746918
   0.8333333333333334 0.9981801 0.0074172835 0.05682755 0.018766368
   0.8416666666666667 0.99813086 0.0077199535 0.058047317 0.017484399
   0.85 0.99805754 0.008212959 0.059549168 0.016356345
   0.8583333333333333 0.997994 0.0084282905 0.060933474 0.014968824
   0.8666666666666667 0.99794734 0.008343086 0.06203129 0.013549777
   0.875 0.9979201 0.008021658 0.062781066 0.012234363
   0.8833333333333333 0.9978794 0.008008123 0.063619524 0.011185087
   0.8916666666666666 0.9978549 0.007998748 0.06411295 0.010541041
   0.9 0.99785954 0.007960641 0.06412531 0.010042887
   0.9083333333333333 0.99785954 0.007960641 0.06412531 0.010042887
   0.9166666666666666 0.9978381 0.008252463 0.06437503 0.010339288
   0.9249999999999999 0.9978095 0.00818203 0.06476731 0.01069579
   0.9333333333333333 0.99774605 0.007996382 0.065628424 0.011481627
   0.9416666666666667 0.99769676 0.007414518 0.06628864 0.012328796
   0.95 0.9976729 0.0065910206 0.06657304 0.013164991
   0.9583333333333334 0.9976612 0.006166794 0.066707954 0.013570707
   0.9666666666666667 0.9976421 0.005344623 0.06693011 0.014215964
   0.975 0.99759996 0.004812775 0.06742481 0.015000407
   0.9833333333333333 0.9975772 0.004484532 0.067688085 0.015424426
   0.9916666666666667 0.99756837 0.0039673382 0.06780886 0.015607214
   1.0 0.99756837 0.0039673382 0.06780886 0.015607214
   1.0083333333333333 0.99758047 0.0038939987 0.06775416 0.015078945
   1.0166666666666666 0.99761546 0.0036802543 0.06734024 0.014668778
   1.025 0.99765974 0.0035905405 0.06671577 0.014530757
   1.0333333333333332 0.99773085 0.0034346865 0.06570225 0.014304706
   1.0416666666666667 0.9978173 0.0034205292 0.064393796 0.014225653
   1.05 0.9978984 0.0030648864 0.06317955 0.014062174
   1.0583333333333333 0.99796873 0.0024153716 0.062147368 0.013792553
   1.0666666666666667 0.99803615 0.0018631001 0.0610595 0.013860667
   1.075 0.9980932 0.001047137 0.0601611 0.013765416
   1.0833333333333333 0.99814427 3.0248816E-4 0.05925639 0.014021366
   1.0916666666666666 0.99818826 -6.548862E-4 0.05850879 0.014019396
   1.1 0.99821204 -0.001788449 0.05807972 0.014009039
   1.1083333333333334 0.99821997 -0.0029207668 0.057822146 0.014318671
   1.1166666666666667 0.99820733 -0.00401398 0.057836253 0.014863799
   1.125 0.9981818 -0.0049375235 0.05798601 0.015694054
   1.1333333333333333 0.99816245 -0.006111452 0.05804726 0.016275609
   1.1416666666666666 0.99812263 -0.007192379 0.05837292 0.017089047
   1.15 0.99806714 -0.008060058 0.058887698 0.018146466
   1.1583333333333332 0.99800557 -0.0085575795 0.05949041 0.01930244
   1.1666666666666667 0.997981 -0.008776003 0.05972299 0.019750567
   1.175 0.9979314 -0.009260321 0.060183868 0.020617396
   1.1833333333333333 0.99789214 -0.00971183 0.06055954 0.021201089
   1.1916666666666667 0.997868 -0.010019296 0.06078472 0.021546511
   1.2 0.99783975 -0.010006182 0.06106529 0.022061288
   1.2083333333333333 0.99783975 -0.010006182 0.06106529 0.022061288
   1.2166666666666666 0.9978684 -0.009751733 0.060657687 0.022004629
   1.225 0.99789983 -0.009829697 0.06024179 0.02168426
   1.2333333333333334 0.9979725 -0.010024415 0.059260264 0.020943336
   1.2416666666666667 0.9980524 -0.009877226 0.05817667 0.020230988
   1.25 0.9981297 -0.0099961115 0.056987885 0.019737042
   1.2583333333333333 0.99819386 -0.010448148 0.05594284 0.01924067
   1.2666666666666666 0.9982586 -0.010653344 0.054819304 0.019002276
   1.275 0.9983209 -0.010566875 0.05369563 0.018988917
   1.2833333333333332 0.99838495 -0.01055711 0.052626524 0.018614922
   1.2916666666666667 0.99844664 -0.010269417 0.05154941 0.018478595
   1.3 0.99849933 -0.009827163 0.05053766 0.018667499
   1.3083333333333333 0.99855477 -0.009731541 0.04941075 0.018767625
   1.3166666666666667 0.99859995 -0.0095374705 0.048351202 0.019217588
   1.325 0.99865466 -0.00954653 0.047140483 0.019377897
   1.3333333333333333 0.9987092 -0.009187735 0.04594599 0.01960876
   1.3416666666666666 0.9987517 -0.008635713 0.04489138 0.020129247
   1.35 0.9987846 -0.0077868965 0.044046618 0.020702867
   1.3583333333333334 0.99880874 -0.007207105 0.04318491 0.021545442
   1.3666666666666667 0.9988181 -0.0064129103 0.042618763 0.0224702
   1.375 0.9988224 -0.0060475 0.042345766 0.02289441
   1.3833333333333333 0.99882966 -0.005394819 0.04183938 0.023657937
   1.3916666666666666 0.9988225 -0.004520055 0.04154358 0.024644123
   1.4 0.99879926 -0.0035659757 0.04161591 0.025600368
   1.4083333333333332 0.998761 -0.002630869 0.04206011 0.026467836
   1.4166666666666667 0.9987166 -0.0019851124 0.042428285 0.027587662
   1.425 0.9986684 -0.0011659653 0.04302668 0.02843898
   1.4333333333333333 0.9986289 -3.3782137E-4 0.043271545 0.02945701
   1.4416666666666667 0.9985779 1.7497952E-4 0.043621775 0.030648487
   1.45 0.99851567 4.8880465E-4 0.044268485 0.031726234
   1.4583333333333333 0.9984813 6.52624E-4 0.044618055 0.03230981
   1.4666666666666666 0.9984259 8.905065E-4 0.045176804 0.033226468
   1.475 0.99837065 0.0014899294 0.04576769 0.034046404
   1.4833333333333334 0.9983313 0.0018680494 0.046195053 0.03459948
   1.4916666666666667 0.9982715 0.0024298392 0.046844944 0.03540686
   1.5 0.99819887 0.0026762327 0.047645345 0.03635681
   1.5083333333333333 0.9981196 0.00298286 0.04872778 0.0370677
   1.5166666666666666 0.9980431 0.0028521265 0.04977681 0.037737187
   1.525 0.9979678 0.0024133197 0.050600886 0.03865221
   1.5333333333333332 0.99788386 0.0023908427 0.051428385 0.039714813
   1.5416666666666667 0.9978444 0.0023704437 0.051815137 0.040201835
   1.55 0.9977792 0.0023095948 0.052447915 0.040994048
   1.5583333333333333 0.9976939 0.0023796358 0.053409234 0.04181721
   1.5666666666666667 0.99761295 0.0021453432 0.054432355 0.042437203
   1.575 0.99752843 0.0022316922 0.055365037 0.043205515
   1.5833333333333333 0.99744487 0.001948547 0.05627948 0.043961458
   1.5916666666666666 0.99736893 0.001317283 0.057110727 0.044630233
   1.6 0.99730706 3.9664115E-4 0.05782354 0.045109566
   1.6083333333333334 0.99723595 -3.7137838E-4 0.05842676 0.045898404
   1.6166666666666667 0.99717766 -0.001430726 0.05893235 0.04649405
   1.625 0.9971392 -0.0026991046 0.059244826 0.04686278
   1.6333333333333333 0.9971243 -0.0040917424 0.059333615 0.046966676
   1.6416666666666666 0.9971172 -0.0048023094 0.05936826 0.047006607
   1.65 0.99710613 -0.005953065 0.059414953 0.0470503
   1.6583333333333332 0.9970829 -0.007432348 0.05948127 0.04724847
   1.6666666666666667 0.9970339 -0.008810135 0.059708897 0.04775663
   1.675 0.99701256 -0.009459684 0.059802957 0.04795962
   1.6833333333333333 0.99701804 -0.010090632 0.0597059 0.04783781
   1.6916666666666667 0.99699533 -0.010670572 0.059927467 0.047908098
   1.7 0.9969482 -0.011928485 0.060373973 0.048031513
   1.7083333333333333 0.9968685 -0.013164585 0.061111305 0.04842896
   1.7166666666666666 0.9967744 -0.01405724 0.06199366 0.04899052
   1.7249999999999999 0.99670553 -0.014958699 0.06275797 0.04915027
   1.7333333333333334 0.996665 -0.015502292 0.063201755 0.049234945
   1.7416666666666667 0.99666893 -0.01592396 0.06320968 0.049010254
   1.75 0.99670154 -0.016140794 0.06276768 0.048843455
   1.7583333333333333 0.9967392 -0.016182927 0.062174335 0.048820153
   1.7666666666666666 0.9968146 -0.016267667 0.060984354 0.048753332
   1.775 0.99691355 -0.016369144 0.05979556 0.048165753
   1.7833333333333332 0.99698955 -0.016398361 0.058593705 0.048059337
   1.7916666666666667 0.99706274 -0.016505968 0.057664607 0.047626078
   1.8 0.99712193 -0.016890064 0.0570038 0.047044713
   1.8083333333333333 0.9972143 -0.016965283 0.055983696 0.046278123
   1.8166666666666667 0.99730223 -0.016590772 0.05505049 0.04563433
   1.825 0.99738115 -0.016599195 0.054253694 0.044854213
   1.8333333333333333 0.99745375 -0.017036088 0.053489923 0.043983776
   1.8416666666666666 0.9975304 -0.017343327 0.0529533 0.042757723
   1.8499999999999999 0.99760616 -0.017390685 0.052674767 0.04129064
   1.8583333333333334 0.997696 -0.017459234 0.052012566 0.0399073
   1.8666666666666667 0.99778223 -0.017166356 0.05149652 0.038523503
   1.875 0.9978507 -0.016695654 0.0513334 0.03715024
   1.8833333333333333 0.9979125 -0.016632082 0.051105957 0.035807323
   1.8916666666666666 0.9979477 -0.01655837 0.051253084 0.03463236
   1.9 0.99799764 -0.016466659 0.05102269 0.033559993
   1.9083333333333332 0.9980421 -0.015982868 0.05109313 0.032342084
   1.9166666666666667 0.9980632 -0.01575973 0.051123302 0.031747684
   1.925 0.9980745 -0.015226134 0.051390912 0.031216621
   1.9333333333333333 0.9980745 -0.015226134 0.051390912 0.031216621
   1.9416666666666667 0.9980745 -0.015226134 0.051390912 0.031216621
   1.95 0.9980745 -0.015226134 0.051390912 0.031216621
   1.9583333333333333 0.9980745 -0.015226134 0.051390912 0.031216621
   1.9666666666666666 0.9980745 -0.015226134 0.051390912 0.031216621
   1.9749999999999999 0.9980745 -0.015226134 0.051390912 0.031216621
   1.9833333333333334 0.9980745 -0.015226134 0.051390912 0.031216621
   1.9916666666666667 0.9980745 -0.015226134 0.051390912 0.031216621
   2.0 0.9980745 -0.015226134 0.051390912 0.031216621
   2.0083333333333333 0.9980745 -0.015226134 0.051390912 0.031216621
   2.0166666666666666 0.9980745 -0.015226134 0.051390912 0.031216621
   2.025 0.9980745 -0.015226134 0.051390912 0.031216621
   2.033333333333333 0.9980745 -0.015226134 0.051390912 0.031216621
   2.0416666666666665 0.9981568 -0.015462533 0.050457835 0.029965496
   2.05 0.998262 -0.015767526 0.049232986 0.028293699
   2.058333333333333 0.9983249 -0.015955064 0.048475314 0.02725914
   2.0666666666666664 0.9983792 -0.015853148 0.047944147 0.026249465
   2.075 0.99844044 -0.01581862 0.04711421 0.02543053
   2.0833333333333335 0.9984966 -0.01558787 0.046528004 0.024427652
   2.091666666666667 0.9985565 -0.015607177 0.045687694 0.023535518
   2.1 0.99861735 -0.01528147 0.044957425 0.022553368
   2.1083333333333334 0.99867314 -0.014630051 0.04441129 0.021577386
   2.1166666666666667 0.99871486 -0.013901576 0.0442167 0.020499248
   2.125 0.9987642 -0.012982647 0.04377672 0.019624583
   2.1333333333333333 0.99878705 -0.012561504 0.043565664 0.019201644
   2.1416666666666666 0.9988275 -0.0118149575 0.043180242 0.018424626
   2.15 0.99884886 -0.011410054 0.042973246 0.018002048
   2.158333333333333 0.99886584 -0.0108886855 0.04272776 0.017965661
   2.1666666666666665 0.99889183 -0.010668036 0.0421874 0.017931206
   2.175 0.9989145 -0.010283083 0.04187881 0.01761623
   2.183333333333333 0.99893755 -0.009990179 0.04138141 0.01765248
   2.1916666666666664 0.9989471 -0.009793357 0.04102278 0.018055188
   2.2 0.9989642 -0.009429361 0.04035631 0.01878819
   2.2083333333333335 0.9989749 -0.009233402 0.039950505 0.019179055
   2.216666666666667 0.99899405 -0.008881391 0.039195422 0.019893995
   2.225 0.99900407 -0.008697029 0.038775157 0.020292444
   2.2333333333333334 0.9990219 -0.00837219 0.038003057 0.020997653
   2.2416666666666667 0.9990325 -0.008197981 0.037553508 0.021367148
   2.25 0.99905556 -0.008036301 0.03699332 0.021327926
   2.2583333333333333 0.9990732 -0.0075433305 0.036683556 0.021216324
   2.2666666666666666 0.9990784 -0.0069868015 0.03678744 0.020982413
   2.275 0.99907506 -0.006740166 0.037152898 0.020573545
   2.283333333333333 0.9990888 -0.0065267435 0.03712224 0.020022877
   2.2916666666666665 0.9990858 -0.006383585 0.0374639 0.019577077
   2.3 0.99909705 -0.0063634175 0.037470583 0.018989444
   2.308333333333333 0.99909425 -0.006224694 0.037804786 0.018514378
   2.3166666666666664 0.9990886 -0.00598558 0.038404536 0.017642824
   2.325 0.9990693 -0.0055634766 0.039316397 0.016849479
   2.3333333333333335 0.99905884 -0.0053769704 0.04002059 0.01583764
   2.341666666666667 0.99906206 -0.0052943346 0.040393163 0.014674372
   2.35 0.99905473 -0.0049503827 0.04096692 0.013668448
   2.3583333333333334 0.99905163 -0.004933313 0.04140066 0.012547969
   2.3666666666666667 0.9990408 -0.0046135723 0.041984066 0.011555588
   2.375 0.9990337 -0.0046214215 0.04244138 0.0104417745
   2.3833333333333333 0.9990118 -0.004496602 0.04318288 0.009505916
   2.3916666666666666 0.9989843 -0.0040666047 0.044016887 0.008738044
   2.4 0.99896336 -0.003879141 0.044690672 0.007741145
   2.408333333333333 0.99895555 -0.0038039333 0.0450584 0.0065661636
   2.4166666666666665 0.99893314 -0.0035553535 0.045708355 0.0055382517
   2.425 0.99892396 -0.003426823 0.04604788 0.004339617
   2.433333333333333 0.99889976 -0.0031202536 0.046677537 0.0032742815
   2.4416666666666664 0.99888825 -0.0029473375 0.047004458 0.0020293037
   2.45 0.9988631 -0.0025532204 0.047592964 9.237498E-4
   2.4583333333333335 0.99884325 -0.0024763253 0.048020605 -3.1268058E-4
   2.466666666666667 0.9988115 -0.0021543275 0.04867353 -0.0013866193
   2.475 0.99876404 -0.0019834163 0.049611647 -0.0022567871
   2.4833333333333334 0.9987281 -0.001975488 0.050270807 -0.0033357101
   2.4916666666666667 0.99869037 -0.002348428 0.050922405 -0.004350007
   2.5 0.99865884 -0.00306416 0.0514137 -0.0052728034
   2.5083333333333333 0.99863225 -0.0040757162 0.051780853 -0.005983106
   2.5166666666666666 0.9986099 -0.0052872105 0.05205439 -0.0063804337
   2.525 0.9985912 -0.006593566 0.05225919 -0.0064136856
   2.533333333333333 0.99856263 -0.007805649 0.05267086 -0.006128961
   2.5416666666666665 0.9985483 -0.0084064305 0.05286425 -0.005993243
   2.55 0.9985555 -0.008890475 0.052676514 -0.005757602
   2.558333333333333 0.99857044 -0.009048817 0.052416015 -0.005265453
   2.5666666666666664 0.99858606 -0.009507365 0.052053433 -0.0050876443
   2.575 0.9985918 -0.009877528 0.05192512 -0.004547325
   2.5833333333333335 0.9985868 -0.009983874 0.052056324 -0.0038633526
   2.591666666666667 0.998569 -0.009924121 0.05244674 -0.0032922933
   2.6 0.9985507 -0.00961054 0.052875813 -0.002878563
   2.6083333333333334 0.9985422 -0.009097269 0.053141057 -0.002604254
   2.6166666666666667 0.9985241 -0.0088106925 0.05354435 -0.0022255513
   2.625 0.99851644 -0.0083320355 0.053774122 -0.0019496616
   2.6333333333333333 0.99850065 -0.008076889 0.05411921 -0.0015462721
   2.6416666666666666 0.9984897 -0.0076148096 0.054392926 -0.0013217024
   2.65 0.9984894 -0.0070481338 0.054475762 -0.0012955331
   2.658333333333333 0.9984777 -0.006602649 0.054749615 -0.0010723354
   2.6666666666666665 0.9984823 -0.0061233197 0.054726265 -7.960749E-4
   2.675 0.9984895 -0.005597757 0.054650377 -8.1605534E-4
   2.683333333333333 0.9985038 -0.005208836 0.054423805 -0.0010587325
   2.6916666666666664 0.9985214 -0.0048299376 0.054135855 -0.0010227712
   2.7 0.99852854 -0.0044643814 0.05403927 -7.890483E-4
   2.7083333333333335 0.998534 -0.004052018 0.053969715 -8.1629166E-4
   2.716666666666667 0.9985266 -0.0037202172 0.054133162 -6.277266E-4
   2.725 0.998511 -0.0036619166 0.054425903 -3.446863E-4
   2.7333333333333334 0.99849784 -0.0033698913 0.054687347 -2.212755E-4
   2.7416666666666667 0.99848187 -0.003315993 0.054981466 6.0704126E-5
   2.75 0.99847585 -0.0029994112 0.055108245 2.5869423E-4
   2.7583333333333333 0.99847585 -0.0029994112 0.055108245 2.5869423E-4
   2.7666666666666666 0.99847585 -0.0029994112 0.055108245 2.5869423E-4
   2.775 0.99847585 -0.0029994112 0.055108245 2.5869423E-4
   2.783333333333333 0.99847585 -0.0029994112 0.055108245 2.5869423E-4
   2.7916666666666665 0.99847585 -0.0029994112 0.055108245 2.5869423E-4
   2.8 0.99847585 -0.0029994112 0.055108245 2.5869423E-4
   2.808333333333333 0.99847585 -0.0029994112 0.055108245 2.5869423E-4
   2.8166666666666664 0.99847585 -0.0029994112 0.055108245 2.5869423E-4
   2.825 0.99847585 -0.0029994112 0.055108245 2.5869423E-4
   2.8333333333333335 0.99847585 -0.0029994112 0.055108245 2.5869423E-4
   2.841666666666667 0.99847585 -0.0029994112 0.055108245 2.5869423E-4
   2.85 0.99846417 -0.0027897106 0.055328857 4.8375255E-4
   2.8583333333333334 0.99844396 -0.0027760859 0.055691794 6.138057E-4
   2.8666666666666667 0.9984236 -0.0030481534 0.056038283 8.630201E-4
   2.875 0.998415 -0.003607783 0.056155335 0.0010382112
   2.8833333333333333 0.99842745 -0.0042638094 0.055885207 0.0011576316
   2.8916666666666666 0.9984359 -0.004939025 0.055682648 8.806524E-4
   2.9 0.99843436 -0.0057007815 0.055636175 9.6138805E-4
   2.908333333333333 0.998428 -0.006325615 0.0556742 0.0014040861
   2.9166666666666665 0.9984171 -0.0066194492 0.05582166 0.0018539611
   2.925 0.9984029 -0.0067017907 0.05605353 0.0021680335
   2.933333333333333 0.9984029 -0.0067017907 0.05605353 0.0021680335
   2.9416666666666664 0.9984029 -0.0067017907 0.05605353 0.0021680335
   2.95 0.9984029 -0.0067017907 0.05605353 0.0021680335
   2.9583333333333335 0.9984029 -0.0067017907 0.05605353 0.0021680335
   2.966666666666667 0.9984029 -0.0067017907 0.05605353 0.0021680335
   2.975 0.9984029 -0.0067017907 0.05605353 0.0021680335
   2.9833333333333334 0.9984029 -0.0067017907 0.05605353 0.0021680335
   2.9916666666666667 0.9984029 -0.0067017907 0.05605353 0.0021680335
   3.0 0.9984029 -0.0067017907 0.05605353 0.0021680335
   3.0083333333333333 0.9984029 -0.0067017907 0.05605353 0.0021680335
   3.0166666666666666 0.9984029 -0.0067017907 0.05605353 0.0021680335
   3.025 0.9984029 -0.0067017907 0.05605353 0.0021680335
   3.033333333333333 0.9984029 -0.0067017907 0.05605353 0.0021680335
   3.0416666666666665 0.9984029 -0.0067017907 0.05605353 0.0021680335
   3.05 0.9984029 -0.0067017907 0.05605353 0.0021680335
   3.058333333333333 0.9984029 -0.0067017907 0.05605353 0.0021680335
   3.0666666666666664 0.9984029 -0.0067017907 0.05605353 0.0021680335
   3.075 0.9984029 -0.0067017907 0.05605353 0.0021680335
   3.0833333333333335 0.9984029 -0.0067017907 0.05605353 0.0021680335
   3.091666666666667 0.9984029 -0.0067017907 0.05605353 0.0021680335
   3.1 0.9984029 -0.0067017907 0.05605353 0.0021680335
   3.1083333333333334 0.9984029 -0.0067017907 0.05605353 0.0021680335
   3.1166666666666667 0.9984029 -0.0067017907 0.05605353 0.0021680335
   3.125 0.9984029 -0.0067017907 0.05605353 0.0021680335
   3.1333333333333333 0.9984029 -0.0067017907 0.05605353 0.0021680335
   3.1416666666666666 0.9984029 -0.0067017907 0.05605353 0.0021680335
   3.15 0.9984029 -0.0067017907 0.05605353 0.0021680335
   3.158333333333333 0.9984029 -0.0067017907 0.05605353 0.0021680335
   3.1666666666666665 0.9984029 -0.0067017907 0.05605353 0.0021680335
   3.175 0.9984029 -0.0067017907 0.05605353 0.0021680335
   3.183333333333333 0.9984029 -0.0067017907 0.05605353 0.0021680335
   3.1916666666666664 0.9984029 -0.0067017907 0.05605353 0.0021680335
   3.2 0.99839556 -0.0063670753 0.05622223 0.002187368
   3.2083333333333335 0.99837434 -0.0060925493 0.056617815 0.0024438153
   3.216666666666667 0.99836195 -0.005651478 0.056854177 0.0030166965
   3.225 0.9983537 -0.0049147597 0.057049755 0.003322849
   3.2333333333333334 0.99836147 -0.0038800244 0.056957286 0.0039005126
   3.2416666666666667 0.998356 -0.0029047313 0.05708206 0.0043044616
   3.25 0.998356 -0.0029047313 0.05708206 0.0043044616
   3.2583333333333333 0.998356 -0.0029047313 0.05708206 0.0043044616
   3.2666666666666666 0.998356 -0.0029047313 0.05708206 0.0043044616
   3.275 0.998356 -0.0029047313 0.05708206 0.0043044616
   3.283333333333333 0.998356 -0.0029047313 0.05708206 0.0043044616
   3.2916666666666665 0.99834037 -0.0027848098 0.057316996 0.0048450013
   3.3 0.99830556 -0.002548245 0.057816688 0.0060573095
   3.308333333333333 0.9982466 -0.0021977976 0.058601044 0.008052773
   3.3166666666666664 0.9981914 -0.0021785926 0.059181955 0.010325352
   3.3249999999999997 0.9981538 -0.0021858185 0.05954378 0.011780641
   3.3333333333333335 0.99811965 -0.0020323938 0.059887525 0.012904756
   3.341666666666667 0.9980944 -0.0021964235 0.060036078 0.014085743
   3.35 0.99807155 -0.0027271234 0.060128156 0.015177906
   3.3583333333333334 0.9980262 -0.0031174337 0.06057124 0.016282562
   3.3666666666666667 0.9979848 -0.0038722872 0.060932383 0.017278813
   3.375 0.9979561 -0.004916485 0.061084326 0.01811505
   3.3833333333333333 0.9979062 -0.005753141 0.061522774 0.019106679
   3.3916666666666666 0.9978407 -0.006289859 0.06218704 0.020178901
   3.4 0.99778163 -0.007163247 0.06273258 0.021098217
   3.408333333333333 0.99774015 -0.008261332 0.06297306 0.021925643
   3.4166666666666665 0.9977077 -0.009577578 0.063119 0.022440715
   3.425 0.9976986 -0.010957531 0.06288965 0.022854432
   3.433333333333333 0.9976746 -0.012230203 0.06275085 0.023626989
   3.4416666666666664 0.9976725 -0.013586861 0.06229284 0.024178896
   3.4499999999999997 0.9976832 -0.015017368 0.061719775 0.024358165
   3.4583333333333335 0.997672 -0.01641023 0.06134248 0.024865882
   3.466666666666667 0.9976341 -0.01776879 0.061310954 0.02552362
   3.475 0.9976195 -0.019126825 0.060928684 0.026022313
   3.4833333333333334 0.99758166 -0.020400785 0.060803145 0.026788209
   3.4916666666666667 0.997567 -0.021681791 0.060320634 0.027411781
   3.5 0.9975244 -0.023024019 0.06019784 0.028128011
   3.5083333333333333 0.99750465 -0.02437136 0.059719488 0.028707013
   3.5166666666666666 0.99750096 -0.025788173 0.05906367 0.02895252
   3.525 0.9975196 -0.027180372 0.05812947 0.028927954
   3.533333333333333 0.99751765 -0.028624466 0.057285342 0.029284492
   3.5416666666666665 0.99753815 -0.029777126 0.05629648 0.029353324
   3.55 0.9975459 -0.030224157 0.05590766 0.029376568
   3.558333333333333 0.99757093 -0.030465689 0.055506267 0.029036358
   3.5666666666666664 0.99760866 -0.03047835 0.05496496 0.028755156
   3.5749999999999997 0.9976719 -0.030184362 0.054148164 0.028419308
   3.5833333333333335 0.9976719 -0.030184362 0.054148164 0.028419308
   3.591666666666667 0.9976719 -0.030184362 0.054148164 0.028419308
   3.6 0.9976719 -0.030184362 0.054148164 0.028419308
   3.6083333333333334 0.9976719 -0.030184362 0.054148164 0.028419308
   3.6166666666666667 0.9976719 -0.030184362 0.054148164 0.028419308
   3.625 0.99765515 -0.029863715 0.05451069 0.028652254
   3.6333333333333333 0.99765533 -0.029291602 0.054632325 0.029001854
   3.6416666666666666 0.99765825 -0.027802674 0.05490331 0.029843679
   3.65 0.99766386 -0.025874123 0.055189963 0.030844567
   3.658333333333333 0.9976893 -0.023796855 0.055295933 0.03149707
   3.6666666666666665 0.99773115 -0.021671327 0.055262808 0.031762753
   3.675 0.99774694 -0.019574605 0.055623174 0.031998895
   3.683333333333333 0.99777746 -0.017435344 0.05587659 0.03184317
   3.6916666666666664 0.99777806 -0.015394461 0.05650517 0.031766552
   3.6999999999999997 0.9977563 -0.013446492 0.057221994 0.032049187
   3.7083333333333335 0.99774736 -0.01150807 0.057856176 0.031944018
   3.716666666666667 0.9977516 -0.009629742 0.058389623 0.031458378
   3.725 0.9977694 -0.007918402 0.058779143 0.030634688
   3.7333333333333334 0.9977634 -0.0063160136 0.059313748 0.030169502
   3.7416666666666667 0.9977695 -0.005001709 0.059710663 0.029422058
   3.75 0.99779457 -0.003955859 0.05979693 0.028543448
   3.7583333333333333 0.99779403 -0.0029391886 0.060117252 0.028005598
   3.7666666666666666 0.9977757 -0.0019793145 0.060532965 0.02784866
   3.775 0.9977338 -8.582794E-4 0.061108842 0.028148754
   3.783333333333333 0.99771416 -3.478489E-4 0.061370764 0.028283259
   3.7916666666666665 0.9976874 -1.293235E-4 0.061659414 0.02859993
   3.8 0.9976874 -1.293235E-4 0.061659414 0.02859993
   3.808333333333333 0.9976874 -1.293235E-4 0.061659414 0.02859993
   3.8166666666666664 0.9976678 1.1369136E-4 0.06188652 0.028793322
   3.8249999999999997 0.9976531 4.0089432E-4 0.062147167 0.028736534
   3.8333333333333335 0.9976247 9.464542E-4 0.062703386 0.028501987
   3.841666666666667 0.99759877 0.0016103588 0.0634156 0.027795259
   3.85 0.9975981 0.0020742768 0.06379924 0.026894415
   3.8583333333333334 0.9975989 0.0023087421 0.06399778 0.026370456
   3.8666666666666667 0.99760145 0.0027505492 0.06437605 0.025289502
   3.875 0.9976095 0.0032795758 0.06482058 0.023723772
   3.8833333333333333 0.9976218 0.0038432404 0.06532183 0.021659337
   3.8916666666666666 0.9976283 0.0041525476 0.06560719 0.020403445
   3.9 0.9976418 0.004138859 0.065747626 0.019259624
   3.908333333333333 0.99766403 0.003785419 0.06574078 0.018175088
   3.9166666666666665 0.99768764 0.0031070043 0.06566568 0.017256815
   3.925 0.9976933 0.0026503413 0.065859824 0.016234534
   3.933333333333333 0.99772143 0.0021259086 0.065688595 0.015246268
   3.9416666666666664 0.9977695 0.0016038542 0.06516611 0.014382855
   3.9499999999999997 0.9978023 0.001291398 0.064890735 0.01334345
   3.9583333333333335 0.9978127 0.0011073416 0.0649518 0.012241422
   3.966666666666667 0.9978443 8.201534E-4 0.06465667 0.011207668
   3.975 0.99786067 8.190211E-4 0.06458574 0.010104306
   3.9833333333333334 0.99785495 0.0010126127 0.06482759 0.0090496205
   3.9916666666666667 0.99784064 0.0015372307 0.06515715 0.008140566
   4.0 0.99783975 0.0018219845 0.06524935 0.007422639
   4.008333333333333 0.99784124 0.0021354295 0.065334305 0.006301351
   4.016666666666667 0.99785703 0.0021679602 0.065202415 0.0050284606
   4.025 0.9978637 0.0025613175 0.06517043 0.0037704224
   4.033333333333333 0.99789363 0.0028453304 0.064757936 0.002569211
   4.041666666666667 0.9979022 0.0033914456 0.06463274 0.0014962623
   4.05 0.9979148 0.0035657207 0.064445555 2.626541E-4
   4.058333333333334 0.9979036 0.0039355126 0.06459063 -9.942083E-4
   4.066666666666666 0.99790585 0.004581453 0.064484775 -0.0021549603
   4.075 0.9979113 0.0048648687 0.06432487 -0.003429463
   4.083333333333333 0.9978907 0.0051949373 0.06453816 -0.0046891575
   4.091666666666667 0.9978936 0.0055128555 0.064363025 -0.0059524328
   4.1 0.9978762 0.0060923016 0.06446092 -0.0071176575
   4.108333333333333 0.9978673 0.0063828626 0.06450465 -0.0077019734
   4.116666666666666 0.9978831 0.006693417 0.06418264 -0.008072734
   4.125 0.9979059 0.007143713 0.06378256 -0.008035481
   4.133333333333333 0.9979409 0.007268928 0.06325712 -0.0077221254
   4.141666666666667 0.9979794 0.0072886418 0.06263177 -0.00782475
   4.15 0.9980179 0.0069400365 0.06207281 -0.0076860525
   4.158333333333333 0.99805003 0.0067257974 0.06164204 -0.007149046
   4.166666666666667 0.9980638 0.006781744 0.061490647 -0.006442603
   4.175 0.9980606 0.007078601 0.06157222 -0.005811875
   4.183333333333334 0.9980419 0.0074740583 0.061867326 -0.005371911
   4.191666666666666 0.99801624 0.007934044 0.062237933 -0.0052017653
   4.2 0.9979934 0.008195162 0.06259904 -0.0048354417
   4.208333333333333 0.9979737 0.008639184 0.0628659 -0.0046619982
   4.216666666666667 0.99795115 0.00885406 0.06321573 -0.0043468834
   4.225 0.99794155 0.009226624 0.06333338 -0.004044262
   4.233333333333333 0.99792117 0.009418398 0.06365759 -0.0035146906
   4.241666666666666 0.99790037 0.009842936 0.06393228 -0.0032583135
   4.25 0.99790037 0.009842936 0.06393228 -0.0032583135
   4.258333333333333 0.99790037 0.009842936 0.06393228 -0.0032583135
   4.266666666666667 0.99790037 0.009842936 0.06393228 -0.0032583135
   4.275 0.9979137 0.009325768 0.06380521 -0.0031914162
   4.283333333333333 0.99791354 0.008878684 0.063890874 -0.0027750784
   4.291666666666667 0.99791336 0.008113797 0.06402093 -0.002104014
   4.3 0.99792105 0.0070354226 0.064043 -0.0015902582
   4.308333333333334 0.9979146 0.006178578 0.064246036 -8.5348496E-4
   4.316666666666666 0.99791753 0.005122296 0.06429744 -3.8936362E-4
   4.325 0.99790114 0.004192752 0.06461896 2.8564702E-4
   4.333333333333333 0.99785984 0.0033729554 0.06529453 9.767142E-4
   4.341666666666667 0.9978391 0.0029455873 0.06562542 0.0013226684
   4.35 0.9978034 0.0022054578 0.0661802 0.001913201
   4.358333333333333 0.9977779 0.0017887398 0.066562325 0.0023634755
   4.366666666666666 0.9977481 0.0016542439 0.06699317 0.0028104193
   4.375 0.9977129 0.0017628834 0.06749786 0.0031382288
   4.383333333333333 0.9976958 0.0019440121 0.06772706 0.0035157134
   4.391666666666667 0.997657 0.0023819776 0.0682295 0.0044227024
   4.4 0.99763846 0.002592797 0.06846434 0.0048420583
   4.408333333333333 0.99765 0.002718949 0.06825626 0.0053022592
   4.416666666666667 0.9976601 0.0024260334 0.06808299 0.005759132
   4.425 0.997682 0.002493533 0.0677211 0.006193883
   4.433333333333334 0.9977031 0.0028988179 0.06737304 0.0064024213
   4.441666666666666 0.9976967 0.0033276915 0.06741232 0.0067674923
   4.45 0.9976791 0.0038486368 0.06764523 0.0067575527
   4.458333333333333 0.997691 0.0043894476 0.06743493 0.006778124
   4.466666666666667 0.99768275 0.0048565674 0.06748815 0.0071361396
   4.475 0.9976596 0.004975929 0.06776528 0.0076395385
   4.483333333333333 0.9976205 0.0051551955 0.06830764 0.0077954414
   4.491666666666666 0.9975984 0.005619782 0.06855704 0.008110078
   4.5 0.9975586 0.0057546035 0.06908049 0.00846138
   4.508333333333333 0.9975217 0.006200883 0.06956319 0.008542481
   4.516666666666667 0.997479 0.0063829767 0.07011454 0.008877712
   4.525 0.9974467 0.00636395 0.070503056 0.009426137
   4.533333333333333 0.9974103 0.0066276165 0.070933424 0.009857676
   4.541666666666667 0.9973977 0.006875703 0.07103255 0.010241088
   4.55 0.99736667 0.007525187 0.071252614 0.0112338215
   4.558333333333334 0.99736667 0.007525187 0.071252614 0.0112338215
   4.566666666666666 0.99736667 0.007525187 0.071252614 0.0112338215
   4.575 0.99736667 0.007525187 0.071252614 0.0112338215
   4.583333333333333 0.99736667 0.007525187 0.071252614 0.0112338215
   4.591666666666667 0.99736667 0.007525187 0.071252614 0.0112338215
   4.6 0.99736667 0.007525187 0.071252614 0.0112338215
   4.608333333333333 0.99736667 0.007525187 0.071252614 0.0112338215
   4.616666666666666 0.99734664 0.007760006 0.071476966 0.0114230355
   4.625 0.9973418 0.007875834 0.071468905 0.011808846
   4.633333333333333 0.9973547 0.007891275 0.07123535 0.012119494
   4.641666666666667 0.99735004 0.007981202 0.071225554 0.012494612
   4.65 0.99736345 0.008044187 0.07097751 0.012790566
   4.658333333333333 0.99736035 0.008279815 0.0709333 0.013123242
   4.666666666666667 0.9973395 0.0085541615 0.07116274 0.013289677
   4.675 0.9973395 0.0085541615 0.07116274 0.013289677
   4.683333333333334 0.9973395 0.0085541615 0.07116274 0.013289677
   4.691666666666666 0.9973395 0.0085541615 0.07116274 0.013289677
   4.7 0.9973395 0.0085541615 0.07116274 0.013289677
   4.708333333333333 0.9973395 0.0085541615 0.07116274 0.013289677
   4.716666666666667 0.9973395 0.0085541615 0.07116274 0.013289677
   4.725 0.9973395 0.0085541615 0.07116274 0.013289677
   4.733333333333333 0.9973395 0.0085541615 0.07116274 0.013289677
   4.741666666666666 0.9973395 0.0085541615 0.07116274 0.013289677
   4.75 0.9973395 0.0085541615 0.07116274 0.013289677
   4.758333333333333 0.9973395 0.0085541615 0.07116274 0.013289677
   4.766666666666667 0.9973395 0.0085541615 0.07116274 0.013289677
   4.775 0.9973395 0.0085541615 0.07116274 0.013289677
   4.783333333333333 0.9973395 0.0085541615 0.07116274 0.013289677
   4.791666666666667 0.9973395 0.0085541615 0.07116274 0.013289677
   4.8 0.9973395 0.0085541615 0.07116274 0.013289677
   4.808333333333334 0.9973395 0.0085541615 0.07116274 0.013289677
   4.816666666666666 0.9973395 0.0085541615 0.07116274 0.013289677
   4.825 0.9973395 0.0085541615 0.07116274 0.013289677
   4.833333333333333 0.9973395 0.0085541615 0.07116274 0.013289677
   4.841666666666667 0.9973395 0.0085541615 0.07116274 0.013289677
   4.85 0.9973395 0.0085541615 0.07116274 0.013289677
   4.858333333333333 0.9973395 0.0085541615 0.07116274 0.013289677
   4.866666666666666 0.9973395 0.0085541615 0.07116274 0.013289677
   4.875 0.9973395 0.0085541615 0.07116274 0.013289677
   4.883333333333333 0.9973395 0.0085541615 0.07116274 0.013289677
   4.891666666666667 0.9973395 0.0085541615 0.07116274 0.013289677
   4.9 0.9973395 0.0085541615 0.07116274 0.013289677
   4.908333333333333 0.9973395 0.0085541615 0.07116274 0.013289677
   4.916666666666667 0.9973395 0.0085541615 0.07116274 0.013289677
   4.925 0.9973395 0.0085541615 0.07116274 0.013289677
   4.933333333333334 0.9973395 0.0085541615 0.07116274 0.013289677
   4.941666666666666 0.9973395 0.0085541615 0.07116274 0.013289677
   4.95 0.9973395 0.0085541615 0.07116274 0.013289677
   4.958333333333333 0.9973395 0.0085541615 0.07116274 0.013289677
   4.966666666666667 0.9973395 0.0085541615 0.07116274 0.013289677
   4.975 0.9973395 0.0085541615 0.07116274 0.013289677
   4.983333333333333 0.9973395 0.0085541615 0.07116274 0.013289677
   4.991666666666666 0.9973395 0.0085541615 0.07116274 0.013289677
   5.0 0.9973395 0.0085541615 0.07116274 0.013289677
   5.008333333333333 0.9973395 0.0085541615 0.07116274 0.013289677
   5.016666666666667 0.9973395 0.0085541615 0.07116274 0.013289677
   5.025 0.9973395 0.0085541615 0.07116274 0.013289677
</SkeletonInterpolator>
   </keyframe>
   <gaze target="camera" offsetAngle="3.0" offsetDirection="UP" influence="EYES" id="bml1:gaze1" xmlns="http://www.bml-initiative.org/bml/bml-1.0"/>
   <speech id="bml1:speech1" xmlns="http://www.bml-initiative.org/bml/bml-1.0"><text>On Sunday you'll go shopping with your sister in New York. Are you looking forward to that?</text>
   </speech>
</bml>
